Workbook

Sheet Income Statement
A1: VoltDrive Motors — EV Automobile Manufacturer
A2: Income Statement ($ in millions)
B4: FY2024A | C4: FY2025A
A6: Revenue | B6: 3000 | C6: 4500
A7: Revenue Growth % | C7: =(C6-B6)/B6 -> 0.5
A8: Cost of Goods Sold | B8: 2400 | C8: 3375
A9: Gross Profit | B9: =B6-B8 -> 600 | C9: =C6-C8 -> 1125
A10: R&D Expense | B10: 300 | C10: 360
A11: SG&A Expense | B11: 360 | C11: 450
A12: EBITDA | B12: =B9-B10-B11 -> -60 | C12: =C9-C10-C11 -> 315
A13: Depreciation & Amortization | B13: 150 | C13: 200
A14: EBIT | B14: =B12-B13 -> -210 | C14: =C12-C13 -> 115
A15: Interest Expense | B15: 75 | C15: 85
A16: EBT (Pre-tax Income) | B16: =B14-B15 -> -285 | C16: =C14-C15 -> 30
A17: Tax Expense | B17: 0 | C17: 7.5
A18: Net Income | B18: =B16-B17 -> -285 | C18: =C16-C17 -> 22.5
A20: Gross Margin % | B20: =B9/B6 -> 0.2 | C20: =C9/C6 -> 0.25
A21: EBITDA Margin % | B21: =B12/B6 -> -0.02 | C21: =C12/C6 -> 0.07
A22: Net Margin % | B22: =B18/B6 -> -0.095 | C22: =C18/C6 -> 0.005

Sheet Balance Sheet
A1: VoltDrive Motors — EV Automobile Manufacturer
A2: Balance Sheet ($ in millions)
B4: FY2024A | C4: FY2025A
A5: Assets
A6: Cash & Equivalents | B6: 375 | C6: 482.5
A7: Accounts Receivable | B7: 300 | C7: 450
A8: Inventory | B8: 450 | C8: 675
A9: Total Current Assets | B9: =SUM(B6:B8) -> 1125 | C9: =SUM(C6:C8) -> 1607.5
A10: Net PP&E (incl. Gigafactory) | B10: 2625 | C10: 2985
A11: Total Assets | B11: =B9+B10 -> 3750 | C11: =C9+C10 -> 4592.5
A13: Liabilities
A14: Accounts Payable | B14: 360 | C14: 540
A15: Short-term Debt | B15: 190 | C15: 190
A16: Total Current Liabilities | B16: =SUM(B14:B15) -> 550 | C16: =SUM(C14:C15) -> 730
A17: Long-term Debt | B17: 1700 | C17: 1880
A18: Total Liabilities | B18: =B16+B17 -> 2250 | C18: =C16+C17 -> 2610
A20: Equity
A21: Common Stock & APIC | B21: 1875 | C21: 2335
A22: Retained Earnings | B22: -375 | C22: -352.5
A23: Total Equity | B23: =B21+B22 -> 1500 | C23: =C21+C22 -> 1982.5
A25: Total Liabilities & Equity | B25: =B18+B23 -> 3750 | C25: =C18+C23 -> 4592.5
A26: Balance Check (should be 0) | B26: =B11-B25 -> 0 | C26: =C11-C25 -> 0

Sheet Cash Flow Statement
A1: VoltDrive Motors — EV Automobile Manufacturer
A2: Cash Flow Statement ($ in millions)
B4: FY2024A | C4: FY2025A
A5: Operating Activities
A6: Net Income | B6: ='Income Statement'!B18 -> -285 | C6: ='Income Statement'!C18 -> 22.5
A7: Add: D&A | B7: ='Income Statement'!B13 -> 150 | C7: ='Income Statement'!C13 -> 200
A8: (Incr)/Decr in Accounts Receivable | B8: N/A (base year) | C8: =-('Balance Sheet'!C7-'Balance Sheet'!B7) -> -150
A9: (Incr)/Decr in Inventory | B9: N/A (base year) | C9: =-('Balance Sheet'!C8-'Balance Sheet'!B8) -> -225
A10: Incr/(Decr) in Accounts Payable | B10: N/A (base year) | C10: ='Balance Sheet'!C14-'Balance Sheet'!B14 -> 180
A11: Net Cash from Operating Activities | B11: =B6+B7 -> -135 | C11: =SUM(C6:C10) -> 27.5
A13: Investing Activities
A14: Capital Expenditures | B14: -500 | C14: -560
A15: Net Cash from Investing Activities | B15: =B14 -> -500 | C15: =C14 -> -560
A17: Financing Activities
A18: Debt Issued | B18: 700 | C18: 280
A19: Debt Repaid | B19: -50 | C19: -100
A20: Equity Issued | B20: 1200 | C20: 460
A21: Net Cash from Financing Activities | B21: =SUM(B18:B20) -> 1850 | C21: =SUM(C18:C20) -> 640
A23: Net Change in Cash | B23: =B11+B15+B21 -> 1215 | C23: =C11+C15+C21 -> 107.5
A24: Beginning Cash Balance | B24: N/A (base year) | C24: ='Balance Sheet'!B6 -> 375
A25: Ending Cash Balance | B25: ='Balance Sheet'!B6 -> 375 | C25: =C24+C23 -> 482.5
A26: Check vs. Balance Sheet Cash (should be 0) | C26: =C25-'Balance Sheet'!C6 -> 0

Sheet WACC
A1: VoltDrive Motors — WACC Calculation Template
A2: Fill in the yellow input cells and build the formulas in column B. Column D gives guidance only.
A4: Cost of Equity (CAPM)
A5: Risk-Free Rate (Rf) | B5: =0.047 -> 0.047 | D5: e.g., 10-yr Treasury yield
A6: Levered Beta | B6: =(1.62+1.85)/2 -> 1.735 | D6: From comparable EV OEM public betas
A7: Equity Market Risk Premium (Rm – Rf) | B7: ='[1]Implied ERP (Monthly from 9-08)'!$K$216 -> 0.0442 | D7: Historical or implied ERP
A8: Cost of Equity (Ke) | B8: =B5+(B6*B7) -> 0.123687 | D8: Ke = Rf + Beta × ERP
A10: Cost of Debt
A11: Pre-tax Cost of Debt (Kd) | B11: ='Income Statement'!C15/('Balance Sheet'!C15+'Balance Sheet'!C17) -> 0.041062802 | D11: Try: Interest Expense / Total Debt from IS & BS tabs
A12: Marginal Tax Rate (t) | B12: 0.25 | D12: Statutory corporate tax rate
A13: After-tax Cost of Debt | B13: =B11*(1-B12) -> 0.030797101 | D13: Kd × (1 – t)
A15: Capital Structure (Market Value Weights)
A16: Market Value of Equity (E) | B16: ='Balance Sheet'!C23 -> 1982.5 | D16: Share price × shares outstanding (or latest funding round valuation)
A17: Market Value of Debt (D) | B17: ='Balance Sheet'!C15+'Balance Sheet'!C17 -> 2070 | D17: Use Balance Sheet ST + LT Debt (book value proxy)
A18: Total Capital (E + D) | B18: =B16+B17 -> 4052.5
A19: Weight of Equity (E / (E+D)) | B19: =B16/B18 -> 0.48920419
A20: Weight of Debt (D / (E+D)) | B20: =B17/B18 -> 0.51079581
A22: WACC | B22: =B19*B8+B20*B11*(1-B12) -> 0.076239229 | D22: WACC = We × Ke + Wd × Kd × (1–t)

Sheet DCF Valuation
A1: VoltDrive Motors — DCF Valuation Template (Blank — Build the Formulas)
A2: $ in millions. Fill in every white cell below — no formulas are pre-built.
B4: FY2026E | C4: FY2027E | D4: FY2028E | E4: FY2029E | F4: FY2030E | G4: Terminal Year
A6: Revenue | B6: ='Revenue & Cost Drivers'!C13 -> 5400 | C6: ='Revenue & Cost Drivers'!D13 -> 6210 | D6: ='Revenue & Cost Drivers'!E13 -> 6831 | E6: ='Revenue & Cost Drivers'!F13 -> 7514.1 | F6: ='Revenue & Cost Drivers'!G13 -> 7889.805 | G6: =F6*(1+$B$25) -> 8126.4992
A7: Revenue Growth % | B7: ='Revenue & Cost Drivers'!C8 -> 0.2 | C7: ='Revenue & Cost Drivers'!D8 -> 0.15 | D7: ='Revenue & Cost Drivers'!E8 -> 0.1 | E7: ='Revenue & Cost Drivers'!F8 -> 0.1 | F7: ='Revenue & Cost Drivers'!G8 -> 0.05 | G7: =B25 -> 0.03
A8: EBITDA | B8: ='Revenue & Cost Drivers'!C13-'Revenue & Cost Drivers'!C19-'Revenue & Cost Drivers'!C22-'Revenue & Cost Drivers'!C24 -> 408 | C8: ='Revenue & Cost Drivers'!D13-'Revenue & Cost Drivers'!D19-'Revenue & Cost Drivers'!D22-'Revenue & Cost Drivers'!D24 -> 496.8 | D8: ='Revenue & Cost Drivers'!E13-'Revenue & Cost Drivers'!E19-'Revenue & Cost Drivers'!E22-'Revenue & Cost Drivers'!E24 -> 592.02 | E8: ='Revenue & Cost Drivers'!F13-'Revenue & Cost Drivers'!F19-'Revenue & Cost Drivers'!F22-'Revenue & Cost Drivers'!F24 -> 684.618 | F8: ='Revenue & Cost Drivers'!G13-'Revenue & Cost Drivers'!G19-'Revenue & Cost Drivers'!G22-'Revenue & Cost Drivers'!G24 -> 771.4476 | G8: =G6*F9 -> 794.59103
A9: EBITDA Margin % | B9: =B8/B6 -> 0.075555556 | C9: =C8/C6 -> 0.08 | D9: =D8/D6 -> 0.086666667 | E9: =E8/E6 -> 0.091111111 | F9: =F8/F6 -> 0.097777778 | G9: =G8/G6 -> 0.097777778
A10: Less: D&A | B10: ='Capacity Expansion'!C26 -> 238.8 | C10: ='Capacity Expansion'!D26 -> 258.30267 | D10: ='Capacity Expansion'!E26 -> 274.55359 | E10: ='Capacity Expansion'!F26 -> 284.71698 | F10: ='Capacity Expansion'!G26 -> 296.41547 | G10: =F10*(1+B25) -> 305.30793
A11: EBIT | B11: =B8-B10 -> 169.2 | C11: =C8-C10 -> 238.49733 | D11: =D8-D10 -> 317.46641 | E11: =E8-E10 -> 399.90102 | F11: =F8-F10 -> 475.03213 | G11: =G8-G10 -> 489.28309
A12: Less: Taxes on EBIT | B12: =MAX(0,B11*WACC!$B$12) -> 42.3 | C12: =MAX(0,C11*WACC!$B$12) -> 59.624333 | D12: =MAX(0,D11*WACC!$B$12) -> 79.366603 | E12: =MAX(0,E11*WACC!$B$12) -> 99.975255 | F12: =MAX(0,F11*WACC!$B$12) -> 118.75803 | G12: =MAX(0,G11*WACC!$B$12) -> 122.32077
A13: EBIAT (NOPAT) | B13: =B11-B12 -> 126.9 | C13: =C11-C12 -> 178.873 | D13: =D11-D12 -> 238.09981 | E13: =E11-E12 -> 299.92577 | F13: =F11-F12 -> 356.2741 | G13: =G11-G12 -> 366.96232
A14: Add: D&A | B14: =B10 -> 238.8 | C14: =C10 -> 258.30267 | D14: =D10 -> 274.55359 | E14: =E10 -> 284.71698 | F14: =F10 -> 296.41547 | G14: =G10 -> 305.30793
A15: Less: Capital Expenditures | B15: ='Capacity Expansion'!C21 -> 482.58333 | C15: ='Capacity Expansion'!D21 -> 461.43917 | D15: ='Capacity Expansion'!E21 -> 401.59599 | E15: ='Capacity Expansion'!F21 -> 430.94811 | F15: ='Capacity Expansion'!G21 -> 324.40967 | G15: =F15*(1+B25) -> 334.14196
A16: Less: Increase in Net Working Capital | B16: =B6*(('Balance Sheet'!$C$7+'Balance Sheet'!$C$8-'Balance Sheet'!$C$14)/'Income Statement'!$C$6)-('Balance Sheet'!$C$7+'Balance Sheet'!$C$8-'Balance Sheet'!$C$14) -> 117 | C16: =C6*(('Balance Sheet'!$C$7+'Balance Sheet'!$C$8-'Balance Sheet'!$C$14)/'Income Statement'!$C$6)-('Balance Sheet'!$C$7+'Balance Sheet'!$C$8-'Balance Sheet'!$C$14) -> 222.3 | D16: =D6*(('Balance Sheet'!$C$7+'Balance Sheet'!$C$8-'Balance Sheet'!$C$14)/'Income Statement'!$C$6)-('Balance Sheet'!$C$7+'Balance Sheet'!$C$8-'Balance Sheet'!$C$14) -> 303.03 | E16: =E6*(('Balance Sheet'!$C$7+'Balance Sheet'!$C$8-'Balance Sheet'!$C$14)/'Income Statement'!$C$6)-('Balance Sheet'!$C$7+'Balance Sheet'!$C$8-'Balance Sheet'!$C$14) -> 391.833 | F16: =F6*(('Balance Sheet'!$C$7+'Balance Sheet'!$C$8-'Balance Sheet'!$C$14)/'Income Statement'!$C$6)-('Balance Sheet'!$C$7+'Balance Sheet'!$C$8-'Balance Sheet'!$C$14) -> 440.67465 | G16: =G6*(('Balance Sheet'!$C$7+'Balance Sheet'!$C$8-'Balance Sheet'!$C$14)/'Income Statement'!$C$6)-('Balance Sheet'!$C$7+'Balance Sheet'!$C$8-'Balance Sheet'!$C$14) -> 471.44489
A17: Unlevered Free Cash Flow | B17: =B13+B14-B15-B16 -> -233.88333 | C17: =C13+C14-C15-C16 -> -246.5635 | D17: =D13+D14-D15-D16 -> -191.9726 | E17: =E13+E14-E15-E16 -> -238.13837 | F17: =F13+F14-F15-F16 -> -112.39475 | G17: =G13+G14-G15-G16 -> -133.31659
A19: Discount Period | B19: =1 -> 1 | C19: =B19+1 -> 2 | D19: =C19+1 -> 3 | E19: =D19+1 -> 4 | F19: =E19+1 -> 5
A20: Discount Factor | B20: =1/(1+WACC!$B$22)^B19 -> 0.92916145 | C20: =1/(1+WACC!$B$22)^C19 -> 0.86334099 | D20: =1/(1+WACC!$B$22)^C19 -> 0.86334099 | E20: =1/(1+WACC!$B$22)^E19 -> 0.74535767 | F20: =1/(1+WACC!$B$22)^F19 -> 0.69255761
A21: PV of Unlevered FCF | B21: =B17*B20 -> -217.31538 | C21: =C17*C20 -> -212.86838 | D21: =D17*D20 -> -165.73781 | E21: =E17*E20 -> -177.49826 | F21: =F17*F20 -> -77.839841
A23: Valuation Summary
A24: Sum of PV of Explicit-Period FCF | B24: =SUM(B21:F21) -> -851.25967
A25: Terminal Growth Rate (g) | B25: =3% -> 0.03
A26: WACC (from WACC tab) | B26: =WACC!B22 -> 0.076239229
A27: Terminal Value (Gordon Growth) | B27: =G17*(1+B25)/(B26-B25) -> -2969.6881
A28: PV of Terminal Value | B28: =B27*E20 -> -2213.4798
A29: Enterprise Value | B29: =B24+B28 -> -3064.7395
A30: Less: Total Debt | B30: ='Balance Sheet'!C15+'Balance Sheet'!C17 -> 2070
A31: Add: Cash & Equivalents | B31: ='Balance Sheet'!C6 -> 482.5
A32: Equity Value | B32: =B29-B30+B31 -> -4652.2395
A33: Diluted Shares Outstanding | B33: 100
A34: Implied Value per Share | B34: =B32/B33 -> -46.522395

Sheet Revenue & Cost Drivers
A1: VoltDrive Motors — Revenue & Cost Drivers Template
A2: Build volume, price, and unit-cost drivers here, then feed the results into the DCF tab.
B4: FY2025A | C4: FY2026E | D4: FY2027E | E4: FY2028E | F4: FY2029E | G4: FY2030E
A6: Revenue Drivers
A7: Vehicles Sold (units, '000) | B7: 100 | C7: =B7*(1+C8) -> 120 | D7: =C7*(1+D8) -> 138 | E7: =D7*(1+E8) -> 151.8 | F7: =E7*(1+F8) -> 166.98 | G7: =F7*(1+G8) -> 175.329
A8: Unit Growth % | C8: 0.2 | D8: 0.15 | E8: 0.1 | F8: 0.1 | G8: 0.05
A9: Average Selling Price (ASP, $'000/unit) | B9: =4500/$B$7 -> 45 | C9: =B9*(1+C10) -> 45 | D9: =C9*(1+D10) -> 45 | E9: =D9*(1+E10) -> 45 | F9: =E9*(1+F10) -> 45 | G9: =F9*(1+G10) -> 45
A10: ASP Growth % | C10: 0 | D10: 0 | E10: 0 | F10: 0 | G10: 0
A11: Revenue from Vehicle Sales ($mm) | B11: 4500 | C11: =C7*C9 -> 5400 | D11: =D7*D9 -> 6210 | E11: =E7*E9 -> 6831 | F11: =F7*F9 -> 7514.1 | G11: =G7*G9 -> 7889.805
A12: Other Revenue (services, software, energy) ($mm) | B12: 0 | C12: 0 | D12: 0 | E12: 0 | F12: 0 | G12: 0
A13: Total Revenue ($mm) | B13: =B11+B12 -> 4500 | C13: =C11+C12 -> 5400 | D13: =D11+D12 -> 6210 | E13: =E11+E12 -> 6831 | F13: =F11+F12 -> 7514.1 | G13: =G11+G12 -> 7889.805
A15: Cost Drivers
A16: Battery Cost per Unit ($'000) | B16: 8.8 | C16: 8.5 | D16: 8.3 | E16: 8 | F16: 7.8 | G16: 7.5
A17: Other Materials/Assembly Cost per Unit ($'000) | B17: =25 -> 25 | C17: 25 | D17: 25 | E17: 25 | F17: 25 | G17: 25
A18: Total Variable Cost per Unit ($'000) | B18: =B16+B17 -> 33.8 | C18: =C16+C17 -> 33.5 | D18: =D16+D17 -> 33.3 | E18: =E16+E17 -> 33 | F18: =F16+F17 -> 32.8 | G18: =G16+G17 -> 32.5
A19: COGS ($mm) | B19: =B7*B18 -> 3380 | C19: =C7*C18 -> 4020 | D19: =D7*D18 -> 4595.4 | E19: =E7*E18 -> 5009.4 | F19: =F7*F18 -> 5476.944 | G19: =G7*G18 -> 5698.1925
A20: Gross Margin % | B20: =(B13-B19)/B13 -> 0.24888889 | C20: =(C13-C19)/C13 -> 0.25555556 | D20: =(D13-D19)/D13 -> 0.26 | E20: =(E13-E19)/E13 -> 0.26666667 | F20: =(F13-F19)/F13 -> 0.27111111 | G20: =(G13-G19)/G13 -> 0.27777778
A21: R&D as % of Revenue | B21: 0.08 | C21: 0.08 | D21: 0.08 | E21: 0.08 | F21: 0.08 | G21: 0.08
A22: R&D Expense ($mm) | B22: =B13*B21 -> 360 | C22: =C13*C21 -> 432 | D22: =D13*D21 -> 496.8 | E22: =E13*E21 -> 546.48 | F22: =F13*F21 -> 601.128 | G22: =G13*G21 -> 631.1844
A23: SG&A as % of Revenue | B23: 0.1 | C23: 0.1 | D23: 0.1 | E23: 0.1 | F23: 0.1 | G23: 0.1
A24: SG&A Expense ($mm) | B24: =B13*B23 -> 450 | C24: =C13*C23 -> 540 | D24: =D13*D23 -> 621 | E24: =E13*E23 -> 683.1 | F24: =F13*F23 -> 751.41 | G24: =G13*G23 -> 788.9805

Sheet Capacity Expansion
A1: VoltDrive Motors — Capacity Expansion Template
A2: Link required capacity to unit sales from the Revenue & Cost Drivers tab, then size capex to close any capacity gap.
B4: FY2025A | C4: FY2026E | D4: FY2027E | E4: FY2028E | F4: FY2029E | G4: FY2030E
A6: Demand Side
A7: Required Units Sold (from Drivers tab, '000) | B7: ='Revenue & Cost Drivers'!B7 -> 100 | C7: ='Revenue & Cost Drivers'!C7 -> 120 | D7: ='Revenue & Cost Drivers'!D7 -> 138 | E7: ='Revenue & Cost Drivers'!E7 -> 151.8 | F7: ='Revenue & Cost Drivers'!F7 -> 166.98 | G7: ='Revenue & Cost Drivers'!G7 -> 175.329
A8: Required Annual Capacity (units, '000) | B8: =B7/B9 -> 111.11111 | C8: =C7/C9 -> 133.33333 | D8: =D7/D9 -> 153.33333 | E8: =E7/E9 -> 168.66667 | F8: =F7/F9 -> 185.53333 | G8: =G7/G9 -> 194.81
A9: Utilization Target % | B9: =90% -> 0.9 | C9: =90% -> 0.9 | D9: =90% -> 0.9 | E9: =90% -> 0.9 | F9: =90% -> 0.9 | G9: =90% -> 0.9
A11: Supply Side
A12: Existing Installed Capacity, Beginning (units, '000) | B12: =100 -> 100 | C12: =B8 -> 111.11111 | D12: =C8 -> 133.33333 | E12: =D8 -> 153.33333 | F12: =E8 -> 168.66667 | G12: =F8 -> 185.53333
A13: Capacity Gap (Required – Existing) | B13: =MAX(0,B8-B12) -> 11.111111 | C13: =MAX(0,C8-C12) -> 22.222222 | D13: =MAX(0,D8-D12) -> 20 | E13: =MAX(0,E8-E12) -> 15.333333 | F13: =MAX(0,F8-F12) -> 16.866667 | G13: =MAX(0,G8-G12) -> 9.2766667
A14: New Capacity to be Added (units, '000) | B14: =B13 -> 11.111111 | C14: =C13 -> 22.222222 | D14: =D13 -> 20 | E14: =E13 -> 15.333333 | F14: =F13 -> 16.866667 | G14: =G13 -> 9.2766667
A15: Installed Capacity, Ending (units, '000) | B15: =B12+B13 -> 111.11111 | C15: =C12+C13 -> 133.33333 | D15: =D12+D13 -> 153.33333 | E15: =E12+E13 -> 168.66667 | F15: =F12+F13 -> 185.53333 | G15: =G12+G13 -> 194.81
A17: Capex Sizing
A18: Capex per Unit of New Capacity ($mm per '000 units) | B18: =15 -> 15 | C18: =15 -> 15 | D18: =15 -> 15 | E18: =15 -> 15 | F18: =15 -> 15 | G18: =15 -> 15
A19: Growth / Expansion Capex ($mm) | B19: =360 -> 360 | C19: =C14*C18 -> 333.33333 | D19: =D14*D18 -> 300 | E19: =E14*E18 -> 230 | F19: =F14*F18 -> 253 | G19: =G14*G18 -> 139.15
A20: Maintenance Capex ($mm) | B20: =200 -> 200 | C20: =B27*0.05 -> 149.25 | D20: =C27*0.05 -> 161.43917 | E20: =D27*0.05 -> 171.59599 | F20: =E27*0.05 -> 177.94811 | G20: =F27*0.05 -> 185.25967
A21: Total Capex ($mm) | B21: =B19+B20 -> 560 | C21: =C19+C20 -> 482.58333 | D21: =D19+D20 -> 461.43917 | E21: =E19+E20 -> 401.59599 | F21: =F19+F20 -> 430.94811 | G21: =G19+G20 -> 324.40967
A23: PP&E Roll-forward
A24: Net PP&E, Beginning ($mm) | B24: ='Balance Sheet'!B10 -> 2625 | C24: =B27 -> 2985 | D24: =C27 -> 3228.7833 | E24: =D27 -> 3431.9198 | F24: =E27 -> 3558.9622 | G24: =F27 -> 3705.1934
A25: Add: Total Capex ($mm) | B25: ='Cash Flow Statement'!C14 -> -560 | C25: =C21 -> 482.58333 | D25: =D21 -> 461.43917 | E25: =E21 -> 401.59599 | F25: =F21 -> 430.94811 | G25: =G21 -> 324.40967
A26: Less: D&A ($mm) | B26: ='Income Statement'!C13 -> 200 | C26: =C24*0.08 -> 238.8 | D26: =D24*0.08 -> 258.30267 | E26: =E24*0.08 -> 274.55359 | F26: =F24*0.08 -> 284.71698 | G26: =G24*0.08 -> 296.41547
A27: Net PP&E, Ending ($mm) | B27: =B24+(-B25)-B26 -> 2985 | C27: =C24+C25-C26 -> 3228.7833 | D27: =D24+D25+-D26 -> 3431.9198 | E27: =E24+E25-E26 -> 3558.9622 | F27: =F24+F25-F26 -> 3705.1934 | G27: =G24+G25-G26 -> 3733.1876

Sheet Debt Schedule
A1: VoltDrive Motors — Debt Schedule Template
A2: Build opening/closing balances, draws, and interest for each tranche; link interest expense back to the Income Statement.
B4: FY2025A | C4: FY2026E | D4: FY2027E | E4: FY2028E | F4: FY2029E | G4: FY2030E
A6: Short-Term Debt / Revolver
A7: Beginning Balance | B7: ='Balance Sheet'!B15 -> 190 | C7: =B10 -> 190 | D7: =C10 -> 190 | E7: =D10 -> 190 | F7: =E10 -> 190 | G7: =F10 -> 190
A8: Draws | B8: =0 -> 0 | C8: 0 | D8: 0 | E8: 0 | F8: 0 | G8: 0
A9: Repayments | B9: 0 | C9: 0 | D9: 0 | E9: 0 | F9: 0 | G9: 0
A10: Ending Balance | B10: =B7+B8-B9 -> 190 | C10: =C7+C8-C9 -> 190 | D10: =D7+D8-D9 -> 190 | E10: =E7+E8-E9 -> 190 | F10: =F7+F8-F9 -> 190 | G10: =G7+G8-G9 -> 190
A11: Interest Rate % | B11: 0.05 | C11: 0.05 | D11: 0.05 | E11: 0.05 | F11: 0.05 | G11: 0.05
A12: Interest Expense | B12: =B7*B11 -> 9.5 | C12: =C7*C11 -> 9.5 | D12: =D7*D11 -> 9.5 | E12: =E7*E11 -> 9.5 | F12: =F7*F11 -> 9.5 | G12: =G7*G11 -> 9.5
A14: Long-Term Debt / Term Loan
A15: Beginning Balance | B15: ='Balance Sheet'!B17 -> 1700 | C15: =B18 -> 1880 | D15: =C18 -> 1786 | E15: =D18 -> 1696.7 | F15: =E18 -> 1611.865 | G15: =F18 -> 1531.2717
A16: New Issuance (funds capex/expansion) | B16: ='Balance Sheet'!C17-'Balance Sheet'!B17 -> 180 | C16: 0 | D16: 0 | E16: 0 | F16: 0 | G16: 0
A17: Scheduled Repayments | B17: 0 | C17: =C15*0.05 -> 94 | D17: =D15*0.05 -> 89.3 | E17: =E15*0.05 -> 84.835 | F17: =F15*0.05 -> 80.59325 | G17: =G15*0.05 -> 76.563587
A18: Ending Balance | B18: =B15+B16-B17 -> 1880 | C18: =C15+C16-C17 -> 1786 | D18: =D15+D16-D17 -> 1696.7 | E18: =E15+E16-E17 -> 1611.865 | F18: =F15+F16-F17 -> 1531.2717 | G18: =G15+G16-G17 -> 1454.7082
A19: Interest Rate % | B19: =('Income Statement'!C15-9.5)/B15 -> 0.044411765 | C19: =4.5% -> 0.045 | D19: =4.5% -> 0.045 | E19: =4.5% -> 0.045 | F19: =4.5% -> 0.045 | G19: =4.5% -> 0.045
A20: Interest Expense | B20: =B15*B19 -> 75.5 | C20: =C15*C19 -> 84.6 | D20: =D15*D19 -> 80.37 | E20: =E15*E19 -> 76.3515 | F20: =F15*F19 -> 72.533925 | G20: =G15*G19 -> 68.907229
A22: Total Debt Summary
A23: Total Debt, Ending Balance | B23: =B10+B18 -> 2070 | C23: =C10+C18 -> 1976 | D23: =D10+D18 -> 1886.7 | E23: =E10+E18 -> 1801.865 | F23: =F10+F18 -> 1721.2717 | G23: =G10+G18 -> 1644.7082
A24: Total Interest Expense | B24: =B12+B20 -> 85 | C24: =C12+C20 -> 94.1 | D24: =D12+D20 -> 89.87 | E24: =E12+E20 -> 85.8515 | F24: =F12+F20 -> 82.033925 | G24: =G12+G20 -> 78.407229
A25: Cash Balance (min cash / sweep check)
